irreceiver/__init__.py
irreceiver/irreceiver.py
irreceiver-0.9.5.dist-info/METADATA
irreceiver-0.9.5.dist-info/WHEEL
irreceiver-0.9.5.dist-info/top_level.txt
irreceiver-0.9.5.dist-info/RECORD
