Metadata-Version: 2.1
Name: irreceiver
Version: 0.9.5
Summary: A module to parse the NEC IR remote control protocol in Python
Home-page: https://github.com/computersarecool/irreceiver
Author: Willy Nolan
Author-email: contact@interactiondepartment.com
License: MIT
Platform: UNKNOWN
